{
    "githashes": [
        {
            "repo_url": "git@gitlab.com:thomas.heritage/rules-processor.git", 
            "commit": "166376bf137355d62ce224b027a833230b3c0529"
        }, 
        {
            "repo_url": "git@gitlab.com:mglanville/rules-revision-ideas.git", 
            "commit": "1f9e005bd6f0641bd868722b0e5aff9c3c55607a"
        }, 
        {
            "repo_url": "git@gitlab.com:thomas.heritage/rules-components-amwa-01.git", 
            "commit": "53c2f7ef1511db5449a36f4415b43b935cc3ef73"
        }, 
        {
            "repo_url": "git@gitlab.com:mglanville/amwa-specs.git", 
            "commit": "950291efc23bca8acec6c143d8058170138cd513"
        }
    ]
}